samila/__init__.py
samila/__main__.py
samila/cli.py
samila/errors.py
samila/functions.py
samila/genimage.py
samila/params.py
samila/test.py
samila-1.6.dist-info/licenses/AUTHORS.md
samila-1.6.dist-info/licenses/LICENSE
samila-1.6.dist-info/METADATA
samila-1.6.dist-info/WHEEL
samila-1.6.dist-info/entry_points.txt
samila-1.6.dist-info/top_level.txt
samila-1.6.dist-info/RECORD
