Metadata-Version: 2.4
Name: samila
Version: 1.6
Summary: A Generative Art Generator
Home-page: https://www.samila.site
Download-URL: https://github.com/sepandhaghighi/samila/tarball/v1.6
Author: Samila Development Team
Author-email: info@samila.site
License: MIT
Project-URL: Source, https://github.com/sepandhaghighi/samila
Project-URL: Tracker, https://github.com/sepandhaghighi/samila/issues
Project-URL: Discord, https://discord.com/invite/94bz5QGZWb
Keywords: generative generative-art art nft file
Classifier: Development Status :: 5 - Production/Stable
Classifier: Natural Language :: English
Classifier: License :: OSI Approved :: MIT License
Classifier: Operating System :: OS Independent
Classifier: Topic :: Games/Entertainment
Classifier: Topic :: Multimedia
Classifier: Topic :: Multimedia :: Graphics
Classifier: Topic :: Multimedia :: Graphics :: 3D Modeling
Classifier: Topic :: Multimedia :: Graphics :: 3D Rendering
Classifier: Topic :: Scientific/Engineering
Classifier: Topic :: Scientific/Engineering :: Mathematics
Classifier: Topic :: Scientific/Engineering :: Visualization
Classifier: Programming Language :: Python :: 3.7
Classifier: Programming Language :: Python :: 3.8
Classifier: Programming Language :: Python :: 3.9
Classifier: Programming Language :: Python :: 3.10
Classifier: Programming Language :: Python :: 3.11
Classifier: Programming Language :: Python :: 3.12
Classifier: Programming Language :: Python :: 3.13
Requires-Python: >=3.7
License-File: LICENSE
License-File: AUTHORS.md
Requires-Dist: matplotlib>=3.0.0
Requires-Dist: art>=1.8
Requires-Dist: Pillow>=6.2
Dynamic: author
Dynamic: author-email
Dynamic: classifier
Dynamic: description
Dynamic: description-content-type
Dynamic: download-url
Dynamic: home-page
Dynamic: keywords
Dynamic: license
Dynamic: license-file
Dynamic: project-url
Dynamic: requires-dist
Dynamic: requires-python
Dynamic: summary
